lightmd/__init__.py
lightmd/blocks/__init__.py
lightmd/blocks/block.py
lightmd/blocks/bold.py
lightmd/blocks/codeblock.py
lightmd/blocks/element.py
lightmd/blocks/fenced_code_block.py
lightmd/blocks/header.py
lightmd/blocks/horizontal_rule.py
lightmd/blocks/img.py
lightmd/blocks/italic_block.py
lightmd/blocks/link_block.py
lightmd/blocks/list_paragraph.py
lightmd/blocks/paragraph.py
lightmd/blocks/quote.py
lightmd/blocks/strikethrough_block.py
lightmd/parser/__init__.py
lightmd/parser/bold_parser.py
lightmd/parser/codeblock_parser.py
lightmd/parser/fenced_code_block_parser.py
lightmd/parser/header_parser.py
lightmd/parser/horizontal_rule_parser.py
lightmd/parser/img_parser.py
lightmd/parser/italic_block_parser.py
lightmd/parser/link_block_parser.py
lightmd/parser/list_paragraph_parser.py
lightmd/parser/parser.py
lightmd/parser/quote_parser.py
lightmd/parser/strikethrough_block_parser.py
lightmd/parser/text_paragraph_parser.py
lightmd/render/__init__.py
lightmd/render/html_render.py
lightmd-0.0.2.0.dist-info/LICENSE
lightmd-0.0.2.0.dist-info/METADATA
lightmd-0.0.2.0.dist-info/WHEEL
lightmd-0.0.2.0.dist-info/top_level.txt
lightmd-0.0.2.0.dist-info/RECORD
