Metadata-Version: 2.1
Name: lightmd
Version: 0.0.2.0
Summary: This is a light-weighted, purly python made markdown parser and render
Home-page: https://github.com/andysim3d/markdown
Author: andysim3d, jinglongwu, VCneverdie, shawn-lo
License: GPL-3.0 License
Platform: UNKNOWN
